{
  "user": [
    {
      "name": "testUser",
      "email": "test.test@gmx.net",
      "password": "test",
      "id": 1
    },
    {
      "name": "testtest",
      "email": "test2@gmail.com",
      "password": "hallo",
      "id": 2
    },
    {
      "name": "testU",
      "email": "test.test@gmail.com",
      "password": "test",
      "id": 3
    }
  ],
  "password_data": [
    {
      "account": {
        "name": "testUser2",
        "email": "test",
        "password": "PA^^couU)qZKw",
        "url": "test",
        "creationDate": "2023-01-12T10:08:38.435Z"
      },
      "userId": 1,
      "id": 1
    },
    {
      "account": {
        "name": "testuser",
        "email": "testmqil@gmail.com",
        "password": "%IVD1qk4sqgPE",
        "url": "https://accounts.google.com/",
        "creationDate": "2023-01-12T10:55:18.914Z"
      },
      "userId": 2,
      "id": 2
    },
    {
      "account": {
        "name": "test2",
        "email": "test2@gmail.com",
        "password": "6U(sdfhuhi%Rj",
        "url": "https://accounts.google.com/",
        "creationDate": "2023-01-12T11:04:42.477Z"
      },
      "userId": 2,
      "id": 3
    },
    {
      "account": {
        "name": "testUser",
        "email": "t.t@gmx.net",
        "password": "DK%vZLGzBQ#KX",
        "url": "https://www.youtube.com",
        "creationDate": "2023-01-25T15:02:12.917Z"
      },
      "userId": 3,
      "id": 4
    },
    {
      "account": {
        "name": "sucukName",
        "email": "sfsfsf",
        "password": "IsR)xt34jd&yw",
        "url": "sfsfsf",
        "creationDate": "2023-01-25T15:15:36.489Z"
      },
      "userId": 1,
      "id": 5
    }
  ]
}